LICENSE
README.md
pyproject.toml
src/aliyun_mcp_tools/__init__.py
src/aliyun_mcp_tools/calculator.py
src/aliyun_mcp_tools/text_tool.py
src/aliyun_mcp_tools/time_tool.py
src/aliyun_mcp_tools_xiaolin_20260130.egg-info/PKG-INFO
src/aliyun_mcp_tools_xiaolin_20260130.egg-info/SOURCES.txt
src/aliyun_mcp_tools_xiaolin_20260130.egg-info/dependency_links.txt
src/aliyun_mcp_tools_xiaolin_20260130.egg-info/requires.txt
src/aliyun_mcp_tools_xiaolin_20260130.egg-info/top_level.txt