Metadata-Version: 2.4
Name: aliyun-mcp-tools-xiaolin-20260130
Version: 0.1.0
Summary: Basic MCP tools package for Aliyun, without system control or Bafayun functionality
Author-email: Xiaolin Developer <developer@example.com>
License: MIT License
Project-URL: Homepage, https://github.com/example/aliyun-mcp-tools-xiaolin
Project-URL: Repository, https://github.com/example/aliyun-mcp-tools-xiaolin
Classifier: Programming Language :: Python :: 3
Classifier: License :: OSI Approved :: MIT License
Classifier: Operating System :: OS Independent
Classifier: Topic :: Software Development :: Libraries :: Python Modules
Classifier: Intended Audience :: Developers
Requires-Python: >=3.8
License-File: LICENSE
Requires-Dist: mcp
Dynamic: license-file
